huojili/Hello.py
huojili/Name.py
huojili/__init__.py
huojili/turt.py
huojili-0.1.dist-info/LICENSE
huojili-0.1.dist-info/METADATA
huojili-0.1.dist-info/WHEEL
huojili-0.1.dist-info/entry_points.txt
huojili-0.1.dist-info/top_level.txt
huojili-0.1.dist-info/RECORD
