Metadata-Version: 2.1
Name: huojili
Version: 0.1
Summary: not
Home-page: https://github.com/pythonml/douyin_image
Author: huojili
Author-email: 
License: UNKNOWN
Platform: UNKNOWN
Classifier: Programming Language :: Python :: 3
Classifier: License :: OSI Approved :: MIT License
Classifier: Operating System :: OS Independent
License-File: LICENSE
